carlogtt_python_library/__init__.py
carlogtt_python_library/py.typed
carlogtt_python_library/amazon_internal/__init__.py
carlogtt_python_library/amazon_internal/apollo.py
carlogtt_python_library/amazon_internal/bindle.py
carlogtt_python_library/amazon_internal/midway.py
carlogtt_python_library/amazon_internal/midway_selenium.py
carlogtt_python_library/amazon_internal/mirador.py
carlogtt_python_library/amazon_internal/phone_tool.py
carlogtt_python_library/amazon_internal/pipelines.py
carlogtt_python_library/amazon_internal/simt.py
carlogtt_python_library/amazon_internal/tiny_url.py
carlogtt_python_library/aws_boto3/__init__.py
carlogtt_python_library/aws_boto3/aws_lambda.py
carlogtt_python_library/aws_boto3/aws_service_base.py
carlogtt_python_library/aws_boto3/cloud_front.py
carlogtt_python_library/aws_boto3/ec2.py
carlogtt_python_library/aws_boto3/kms.py
carlogtt_python_library/aws_boto3/s3.py
carlogtt_python_library/aws_boto3/secrets_manager.py
carlogtt_python_library/database/__init__.py
carlogtt_python_library/database/database_dynamo.py
carlogtt_python_library/database/database_sql.py
carlogtt_python_library/database/database_utils.py
carlogtt_python_library/database/redis_cache_manager.py
carlogtt_python_library/exceptions/__init__.py
carlogtt_python_library/exceptions/exceptions.py
carlogtt_python_library/logger/__init__.py
carlogtt_python_library/logger/app_logger.py
carlogtt_python_library/utils/__init__.py
carlogtt_python_library/utils/aws_sig_v4_requests.py
carlogtt_python_library/utils/cli_utils.py
carlogtt_python_library/utils/context_managers.py
carlogtt_python_library/utils/decorators.py
carlogtt_python_library/utils/encryption.py
carlogtt_python_library/utils/miscs.py
carlogtt_python_library/utils/string_tools.py
carlogtt_python_library/utils/user_input.py
carlogtt_python_library/utils/validators.py
carlogtt_python_library-1.7.0.dist-info/licenses/LICENSE
carlogtt_python_library-1.7.0.dist-info/METADATA
carlogtt_python_library-1.7.0.dist-info/WHEEL
carlogtt_python_library-1.7.0.dist-info/top_level.txt
carlogtt_python_library-1.7.0.dist-info/RECORD
