Metadata-Version: 2.4
Name: carlogtt_python_library
Version: 1.7.0
Summary: A versatile Python library offering a collection of reusable utility functions designed to streamline common programming tasks and promote code reusability across various projects.
Home-page: https://github.com/64rl0/CarlogttPythonLibrary.git
Author: Carlo Gatti
Author-email: Carlo Gatti <carlo.gatti@me.com>
License-Expression: MIT
Project-URL: Homepage, https://github.com/64rl0/CarlogttPythonLibrary.git
Requires-Python: >=3.9
License-File: LICENSE
Requires-Dist: boto3
Requires-Dist: awscrt
Requires-Dist: cryptography
Requires-Dist: mysql-connector-python
Requires-Dist: redis
Requires-Dist: requests
Requires-Dist: selenium
Requires-Dist: typing-extensions
Requires-Dist: types-cryptography
Requires-Dist: types-requests
Requires-Dist: types-redis
Requires-Dist: types-psycopg2
Requires-Dist: boto3-stubs
Requires-Dist: mypy-boto3
Requires-Dist: mypy-boto3-cloudfront
Requires-Dist: mypy-boto3-dynamodb
Requires-Dist: mypy-boto3-ec2
Requires-Dist: mypy-boto3-kms
Requires-Dist: mypy-boto3-lambda
Requires-Dist: mypy-boto3-s3
Requires-Dist: mypy-boto3-secretsmanager
Provides-Extra: postgres
Requires-Dist: psycopg2; extra == "postgres"
Dynamic: license-file
